{ 
   "playerHeightAdjust" : "0.09034543", 
   "monitorCameraRotation" : { 
      "x" : "13.38539", 
      "y" : "0", 
      "z" : "0"
   }, 
   "useSceneLoadPosition" : "true", 
   "atoms" : [ 
      { 
         "id" : "WindowCamera", 
         "on" : "true", 
         "type" : "WindowCamera", 
         "position" : { 
            "x" : "1.301", 
            "y" : "1.684", 
            "z" : "1.412"
         }, 
         "rotation" : { 
            "x" : "0", 
            "y" : "0", 
            "z" : "0"
         }, 
         "containerPosition" : { 
            "x" : "1.131281", 
            "y" : "0.795909", 
            "z" : "2.745082"
         }, 
         "containerRotation" : { 
            "x" : "3.196422", 
            "y" : "184.273", 
            "z" : "-5.878839E-07"
         }, 
         "storables" : [ 
            { 
               "id" : "CollisionTrigger", 
               "trigger" : { 
                  "startActions" : [ 
                  ], 
                  "transitionActions" : [ 
                  ], 
                  "endActions" : [ 
                  ]
               }
            }, 
            { 
               "id" : "CameraControl", 
               "FOV" : "36.53305"
            }, 
            { 
               "id" : "PluginManager", 
               "plugins" : { 
               }
            }, 
            { 
               "id" : "control", 
               "zRotationLock" : "true", 
               "position" : { 
                  "x" : "1.131281", 
                  "y" : "0.795909", 
                  "z" : "2.745082"
               }, 
               "rotation" : { 
                  "x" : "3.196422", 
                  "y" : "184.273", 
                  "z" : "-5.878839E-07"
               }
            }
         ]
      }, 
      { 
         "id" : "PlayerNavigationPanel", 
         "on" : "true", 
         "type" : "PlayerNavigationPanel", 
         "position" : { 
            "x" : "0.5", 
            "y" : "0", 
            "z" : "0.5"
         }, 
         "rotation" : { 
            "x" : "0", 
            "y" : "0", 
            "z" : "0"
         }, 
         "containerPosition" : { 
            "x" : "0.5", 
            "y" : "0", 
            "z" : "0.5"
         }, 
         "containerRotation" : { 
            "x" : "0", 
            "y" : "0", 
            "z" : "0"
         }, 
         "storables" : [ 
            { 
               "id" : "CollisionTrigger", 
               "trigger" : { 
                  "startActions" : [ 
                  ], 
                  "transitionActions" : [ 
                  ], 
                  "endActions" : [ 
                  ]
               }
            }, 
            { 
               "id" : "PluginManager", 
               "plugins" : { 
               }
            }, 
            { 
               "id" : "control", 
               "position" : { 
                  "x" : "0.5", 
                  "y" : "0", 
                  "z" : "0.5"
               }, 
               "rotation" : { 
                  "x" : "0", 
                  "y" : "0", 
                  "z" : "0"
               }
            }
         ]
      }, 
      { 
         "id" : "CoreControl", 
         "on" : "true", 
         "type" : "CoreControl", 
         "storables" : [ 
            { 
               "id" : "GlobalLighting", 
               "showSkybox" : "true", 
               "masterIntensity" : "0.05000001", 
               "diffuseIntensity" : "0.01", 
               "specularIntensity" : "0.05999994", 
               "camExposure" : "0.02999992", 
               "skyboxIntensity" : "5.424218", 
               "skyName" : "SkyEpicCentreOfTheStorm"
            }, 
            { 
               "id" : "MotionAnimationMaster", 
               "triggers" : [ 
               ]
            }
         ]
      }, 
      { 
         "id" : "[CameraRig]", 
         "on" : "true", 
         "type" : "VRController", 
         "position" : { 
            "x" : "1.146787", 
            "y" : "-1.602267E-10", 
            "z" : "1.844919"
         }, 
         "rotation" : { 
            "x" : "-1.238115E-07", 
            "y" : "202.9495", 
            "z" : "-1.74865E-07"
         }, 
         "storables" : [ 
         ]
      }, 
      { 
         "id" : "Person", 
         "on" : "true", 
         "type" : "Person", 
         "position" : { 
            "x" : "0", 
            "y" : "0", 
            "z" : "0"
         }, 
         "rotation" : { 
            "x" : "0", 
            "y" : "0", 
            "z" : "0"
         }, 
         "containerPosition" : { 
            "x" : "0", 
            "y" : "0", 
            "z" : "0"
         }, 
         "containerRotation" : { 
            "x" : "0", 
            "y" : "0", 
            "z" : "0"
         }, 
         "storables" : [ 
            { 
               "id" : "control", 
               "position" : { 
                  "x" : "0", 
                  "y" : "0", 
                  "z" : "0"
               }, 
               "rotation" : { 
                  "x" : "0", 
                  "y" : "0", 
                  "z" : "0"
               }
            }, 
            { 
               "id" : "hipControl", 
               "localPosition" : { 
                  "x" : "-0.02949035", 
                  "y" : "1.013296", 
                  "z" : "-0.1054706"
               }, 
               "localRotation" : { 
                  "x" : "354.2312", 
                  "y" : "359.7993", 
                  "z" : "358.028"
               }
            }, 
            { 
               "id" : "pelvisControl", 
               "localPosition" : { 
                  "x" : "0.02531607", 
                  "y" : "1.06658", 
                  "z" : "-0.09173346"
               }, 
               "localRotation" : { 
                  "x" : "5.411252", 
                  "y" : "359.9357", 
                  "z" : "357.4568"
               }
            }, 
            { 
               "id" : "chestControl", 
               "positionState" : "Off", 
               "rotationState" : "Off", 
               "localPosition" : { 
                  "x" : "0.1035763", 
                  "y" : "1.249665", 
                  "z" : "-0.1347654"
               }, 
               "localRotation" : { 
                  "x" : "359.1463", 
                  "y" : "350.2533", 
                  "z" : "338.4556"
               }
            }, 
            { 
               "id" : "headControl", 
               "holdPositionSpring" : "48064.16", 
               "holdRotationSpring" : "5048.736", 
               "localPosition" : { 
                  "x" : "0.2176733", 
                  "y" : "1.578491", 
                  "z" : "-0.08162427"
               }, 
               "localRotation" : { 
                  "x" : "32.7735", 
                  "y" : "338.766", 
                  "z" : "356.7603"
               }
            }, 
            { 
               "id" : "rHandControl", 
               "localPosition" : { 
                  "x" : "0.2385772", 
                  "y" : "1.278594", 
                  "z" : "0.1886181"
               }, 
               "localRotation" : { 
                  "x" : "318.6696", 
                  "y" : "161.8865", 
                  "z" : "5.943565"
               }
            }, 
            { 
               "id" : "lHandControl", 
               "localPosition" : { 
                  "x" : "-0.5780728", 
                  "y" : "1.3257", 
                  "z" : "-0.0747622"
               }, 
               "localRotation" : { 
                  "x" : "359.3555", 
                  "y" : "330.2948", 
                  "z" : "340.1414"
               }
            }, 
            { 
               "id" : "rFootControl", 
               "localPosition" : { 
                  "x" : "0.08878738", 
                  "y" : "0.06367558", 
                  "z" : "-0.1247065"
               }, 
               "localRotation" : { 
                  "x" : "15.25148", 
                  "y" : "25.84024", 
                  "z" : "0.8977928"
               }
            }, 
            { 
               "id" : "lFootControl", 
               "localPosition" : { 
                  "x" : "-0.04895984", 
                  "y" : "0.06367502", 
                  "z" : "-0.1021861"
               }, 
               "localRotation" : { 
                  "x" : "15.2514", 
                  "y" : "348.053", 
                  "z" : "359.1021"
               }
            }, 
            { 
               "id" : "neckControl", 
               "localPosition" : { 
                  "x" : "0.2007326", 
                  "y" : "1.494884", 
                  "z" : "-0.1293903"
               }, 
               "localRotation" : { 
                  "x" : "29.46523", 
                  "y" : "341.0815", 
                  "z" : "345.0439"
               }
            }, 
            { 
               "id" : "eyeTargetControl", 
               "mass" : "0.01", 
               "localPosition" : { 
                  "x" : "0", 
                  "y" : "1.7", 
                  "z" : "1"
               }, 
               "localRotation" : { 
                  "x" : "0", 
                  "y" : "0", 
                  "z" : "0"
               }
            }, 
            { 
               "id" : "rNippleControl", 
               "localPosition" : { 
                  "x" : "0.2081217", 
                  "y" : "1.297339", 
                  "z" : "0.03136022"
               }, 
               "localRotation" : { 
                  "x" : "8.239122", 
                  "y" : "204.4209", 
                  "z" : "32.39323"
               }
            }, 
            { 
               "id" : "lNippleControl", 
               "localPosition" : { 
                  "x" : "0.01887259", 
                  "y" : "1.369514", 
                  "z" : "0.0003056899"
               }, 
               "localRotation" : { 
                  "x" : "28.72737", 
                  "y" : "151.0936", 
                  "z" : "8.126377"
               }
            }, 
            { 
               "id" : "testesControl", 
               "localPosition" : { 
                  "x" : "-0.000223991", 
                  "y" : "0.8563702", 
                  "z" : "0.04342289"
               }, 
               "localRotation" : { 
                  "x" : "7.242297", 
                  "y" : "359.9724", 
                  "z" : "359.9438"
               }
            }, 
            { 
               "id" : "penisBaseControl", 
               "localPosition" : { 
                  "x" : "-0.0002126085", 
                  "y" : "0.8751119", 
                  "z" : "0.06262219"
               }, 
               "localRotation" : { 
                  "x" : "7.242297", 
                  "y" : "359.9724", 
                  "z" : "359.9438"
               }
            }, 
            { 
               "id" : "penisMidControl", 
               "localPosition" : { 
                  "x" : "-0.0002260867", 
                  "y" : "0.8715264", 
                  "z" : "0.09055456"
               }, 
               "localRotation" : { 
                  "x" : "7.242297", 
                  "y" : "359.9724", 
                  "z" : "359.9438"
               }
            }, 
            { 
               "id" : "penisTipControl", 
               "localPosition" : { 
                  "x" : "-0.0002396022", 
                  "y" : "0.8679577", 
                  "z" : "0.1186373"
               }, 
               "localRotation" : { 
                  "x" : "7.242297", 
                  "y" : "359.9724", 
                  "z" : "359.9438"
               }
            }, 
            { 
               "id" : "rElbowControl", 
               "localPosition" : { 
                  "x" : "0.4277934", 
                  "y" : "1.189593", 
                  "z" : "0.07677893"
               }, 
               "localRotation" : { 
                  "x" : "320.6713", 
                  "y" : "192.9666", 
                  "z" : "25.03975"
               }
            }, 
            { 
               "id" : "lElbowControl", 
               "localPosition" : { 
                  "x" : "-0.2555149", 
                  "y" : "1.390121", 
                  "z" : "-0.1125202"
               }, 
               "localRotation" : { 
                  "x" : "5.591541", 
                  "y" : "7.473046", 
                  "z" : "12.21988"
               }
            }, 
            { 
               "id" : "rKneeControl", 
               "localPosition" : { 
                  "x" : "0.1048091", 
                  "y" : "0.5299156", 
                  "z" : "-0.03131466"
               }, 
               "localRotation" : { 
                  "x" : "11.08408", 
                  "y" : "16.05312", 
                  "z" : "0.6402569"
               }
            }, 
            { 
               "id" : "lKneeControl", 
               "localPosition" : { 
                  "x" : "-0.0684486", 
                  "y" : "0.5357428", 
                  "z" : "-0.04113121"
               }, 
               "localRotation" : { 
                  "x" : "7.238209", 
                  "y" : "356.6421", 
                  "z" : "2.247071"
               }
            }, 
            { 
               "id" : "rToeControl", 
               "localPosition" : { 
                  "x" : "0.142233", 
                  "y" : "0.01877236", 
                  "z" : "-0.01695462"
               }, 
               "localRotation" : { 
                  "x" : "13.91369", 
                  "y" : "26.18843", 
                  "z" : "2.063762"
               }
            }, 
            { 
               "id" : "lToeControl", 
               "localPosition" : { 
                  "x" : "-0.07745603", 
                  "y" : "0.02018499", 
                  "z" : "0.01487786"
               }, 
               "localRotation" : { 
                  "x" : "14.32691", 
                  "y" : "347.6339", 
                  "z" : "359.535"
               }
            }, 
            { 
               "id" : "abdomenControl", 
               "localPosition" : { 
                  "x" : "0.02295768", 
                  "y" : "1.037166", 
                  "z" : "-0.1250192"
               }, 
               "localRotation" : { 
                  "x" : "359.5315", 
                  "y" : "357.0149", 
                  "z" : "343.6087"
               }
            }, 
            { 
               "id" : "abdomen2Control", 
               "localPosition" : { 
                  "x" : "0.05024649", 
                  "y" : "1.131312", 
                  "z" : "-0.1160071"
               }, 
               "localRotation" : { 
                  "x" : "347.699", 
                  "y" : "358.7954", 
                  "z" : "336.1946"
               }
            }, 
            { 
               "id" : "rThighControl", 
               "localPosition" : { 
                  "x" : "0.105987", 
                  "y" : "0.9669739", 
                  "z" : "-0.1151931"
               }, 
               "localRotation" : { 
                  "x" : "349.7803", 
                  "y" : "7.381787", 
                  "z" : "359.4853"
               }
            }, 
            { 
               "id" : "lThighControl", 
               "localPosition" : { 
                  "x" : "-0.06405294", 
                  "y" : "0.9746442", 
                  "z" : "-0.1146334"
               }, 
               "localRotation" : { 
                  "x" : "351.0128", 
                  "y" : "356.9355", 
                  "z" : "358.9158"
               }
            }, 
            { 
               "id" : "rArmControl", 
               "localPosition" : { 
                  "x" : "0.3152532", 
                  "y" : "1.40229", 
                  "z" : "-0.09540238"
               }, 
               "localRotation" : { 
                  "x" : "350.0341", 
                  "y" : "314.2448", 
                  "z" : "313.2797"
               }
            }, 
            { 
               "id" : "lArmControl", 
               "localPosition" : { 
                  "x" : "0.0264534", 
                  "y" : "1.47699", 
                  "z" : "-0.1334567"
               }, 
               "localRotation" : { 
                  "x" : "4.878557", 
                  "y" : "5.310343", 
                  "z" : "16.83594"
               }
            }, 
            { 
               "id" : "rShoulderControl", 
               "localPosition" : { 
                  "x" : "0.1845531", 
                  "y" : "1.428503", 
                  "z" : "-0.0886893"
               }, 
               "localRotation" : { 
                  "x" : "350.3342", 
                  "y" : "359.5132", 
                  "z" : "3.482756"
               }
            }, 
            { 
               "id" : "lShoulderControl", 
               "localPosition" : { 
                  "x" : "0.154164", 
                  "y" : "1.440156", 
                  "z" : "-0.09379154"
               }, 
               "localRotation" : { 
                  "x" : "346.2258", 
                  "y" : "351.5106", 
                  "z" : "327.097"
               }
            }, 
            { 
               "id" : "PluginManager", 
               "plugins" : { 
               }
            }, 
            { 
               "id" : "geometry", 
               "character" : "Female 3", 
               "clothing" : [ 
                  { 
                     "id" : "Tank Top", 
                     "enabled" : "true"
                  }, 
                  { 
                     "id" : "Shorts", 
                     "enabled" : "true"
                  }
               ], 
               "hair" : "SimV2 Hair", 
               "morphs" : [ 
                  { 
                     "name" : "Labia majora-relaxation", 
                     "value" : "0"
                  }, 
                  { 
                     "name" : "Flirting", 
                     "value" : "0.1460984"
                  }, 
                  { 
                     "name" : "Smile Full Face", 
                     "value" : "0.2549866"
                  }
               ]
            }, 
            { 
               "id" : "hip", 
               "rootPosition" : { 
                  "x" : "0.02382191", 
                  "y" : "1.048365", 
                  "z" : "-0.109861"
               }, 
               "rootRotation" : { 
                  "x" : "359.7118", 
                  "y" : "358.5218", 
                  "z" : "353.5502"
               }
            }, 
            { 
               "id" : "pelvis", 
               "position" : { 
                  "x" : "-8.703838E-05", 
                  "y" : "0.01822935", 
                  "z" : "0.01817435"
               }, 
               "rotation" : { 
                  "x" : "5.504321", 
                  "y" : "2.04759", 
                  "z" : "3.941862"
               }
            }, 
            { 
               "id" : "LabiaTrigger", 
               "trigger" : { 
                  "displayName" : "LabiaTrigger", 
                  "startActions" : [ 
                  ], 
                  "transitionActions" : [ 
                  ], 
                  "endActions" : [ 
                  ]
               }
            }, 
            { 
               "id" : "VaginaTrigger", 
               "trigger" : { 
                  "displayName" : "VaginaTrigger", 
                  "startActions" : [ 
                  ], 
                  "transitionActions" : [ 
                  ], 
                  "endActions" : [ 
                  ]
               }
            }, 
            { 
               "id" : "DeepVaginaTrigger", 
               "trigger" : { 
                  "displayName" : "DeepVaginaTrigger", 
                  "startActions" : [ 
                  ], 
                  "transitionActions" : [ 
                  ], 
                  "endActions" : [ 
                  ]
               }
            }, 
            { 
               "id" : "DeeperVaginaTrigger", 
               "trigger" : { 
                  "displayName" : "DeeperVaginaTrigger", 
                  "startActions" : [ 
                  ], 
                  "transitionActions" : [ 
                  ], 
                  "endActions" : [ 
                  ]
               }
            }, 
            { 
               "id" : "Testes", 
               "position" : { 
                  "x" : "-5.587935E-09", 
                  "y" : "-0.1958989", 
                  "z" : "0.05661093"
               }, 
               "rotation" : { 
                  "x" : "-2.561321E-06", 
                  "y" : "-3.201651E-07", 
                  "z" : "4.40227E-07"
               }
            }, 
            { 
               "id" : "rThigh", 
               "position" : { 
                  "x" : "0.0850637", 
                  "y" : "-0.0977047", 
                  "z" : "-0.01405191"
               }, 
               "rotation" : { 
                  "x" : "344.0945", 
                  "y" : "6.897187", 
                  "z" : "1.379488"
               }
            }, 
            { 
               "id" : "rShin", 
               "position" : { 
                  "x" : "-0.007948274", 
                  "y" : "-0.4449454", 
                  "z" : "0.004170366"
               }, 
               "rotation" : { 
                  "x" : "21.09889", 
                  "y" : "9.326363", 
                  "z" : "2.828848"
               }
            }, 
            { 
               "id" : "rFoot", 
               "position" : { 
                  "x" : "0.004028448", 
                  "y" : "-0.4722193", 
                  "z" : "0.0006152093"
               }, 
               "rotation" : { 
                  "x" : "8.658148", 
                  "y" : "9.123322", 
                  "z" : "359.8358"
               }
            }, 
            { 
               "id" : "rToe", 
               "position" : { 
                  "x" : "0.002902912", 
                  "y" : "-0.006207151", 
                  "z" : "0.1257368"
               }, 
               "rotation" : { 
                  "x" : "354.4465", 
                  "y" : "0.677864", 
                  "z" : "359.551"
               }
            }, 
            { 
               "id" : "rBigToe", 
               "position" : { 
                  "x" : "-0.03142246", 
                  "y" : "0.008008221", 
                  "z" : "0.01136879"
               }, 
               "rotation" : { 
                  "x" : "4.494541", 
                  "y" : "4.709316", 
                  "z" : "356.2693"
               }
            }, 
            { 
               "id" : "rSmallToe1", 
               "position" : { 
                  "x" : "-0.008659201", 
                  "y" : "0.009396468", 
                  "z" : "0.0162856"
               }, 
               "rotation" : { 
                  "x" : "9.34357", 
                  "y" : "3.324982", 
                  "z" : "355.2796"
               }
            }, 
            { 
               "id" : "rSmallToe2", 
               "position" : { 
                  "x" : "0.006968057", 
                  "y" : "0.007802647", 
                  "z" : "0.01691755"
               }, 
               "rotation" : { 
                  "x" : "13.40537", 
                  "y" : "1.195918", 
                  "z" : "355.8529"
               }
            }, 
            { 
               "id" : "rSmallToe3", 
               "position" : { 
                  "x" : "0.01803702", 
                  "y" : "0.002753248", 
                  "z" : "0.01345845"
               }, 
               "rotation" : { 
                  "x" : "15.49609", 
                  "y" : "359.96", 
                  "z" : "352.6501"
               }
            }, 
            { 
               "id" : "rSmallToe4", 
               "position" : { 
                  "x" : "0.03410647", 
                  "y" : "-0.002237549", 
                  "z" : "0.009482657"
               }, 
               "rotation" : { 
                  "x" : "18.32239", 
                  "y" : "356.3707", 
                  "z" : "350.0494"
               }
            }, 
            { 
               "id" : "LGlute", 
               "position" : { 
                  "x" : "-0.05998238", 
                  "y" : "-0.1199637", 
                  "z" : "1.19675E-06"
               }, 
               "rotation" : { 
                  "x" : "9.779846", 
                  "y" : "0.1535957", 
                  "z" : "0.4209707"
               }
            }, 
            { 
               "id" : "Gen1", 
               "position" : { 
                  "x" : "-5.587935E-09", 
                  "y" : "-0.1748865", 
                  "z" : "0.07329444"
               }, 
               "rotation" : { 
                  "x" : "-2.561321E-06", 
                  "y" : "-3.201651E-07", 
                  "z" : "4.40227E-07"
               }
            }, 
            { 
               "id" : "Gen2", 
               "position" : { 
                  "x" : "6.67635E-09", 
                  "y" : "-3.552563E-05", 
                  "z" : "0.02816151"
               }, 
               "rotation" : { 
                  "x" : "0", 
                  "y" : "0", 
                  "z" : "-7.156247E-15"
               }
            }, 
            { 
               "id" : "Gen3", 
               "position" : { 
                  "x" : "-1.704457E-09", 
                  "y" : "8.814095E-08", 
                  "z" : "0.0283087"
               }, 
               "rotation" : { 
                  "x" : "0", 
                  "y" : "0", 
                  "z" : "0"
               }
            }, 
            { 
               "id" : "RGlute", 
               "position" : { 
                  "x" : "0.05995994", 
                  "y" : "-0.1200834", 
                  "z" : "7.549301E-06"
               }, 
               "rotation" : { 
                  "x" : "9.812076", 
                  "y" : "0.06869182", 
                  "z" : "359.6489"
               }
            }, 
            { 
               "id" : "lThigh", 
               "position" : { 
                  "x" : "-0.08515005", 
                  "y" : "-0.09755027", 
                  "z" : "-0.0140282"
               }, 
               "rotation" : { 
                  "x" : "345.7592", 
                  "y" : "356.2926", 
                  "z" : "1.827881"
               }
            }, 
            { 
               "id" : "lShin", 
               "position" : { 
                  "x" : "0.007960239", 
                  "y" : "-0.4449446", 
                  "z" : "0.004165612"
               }, 
               "rotation" : { 
                  "x" : "16.22805", 
                  "y" : "0.01231339", 
                  "z" : "3.328461"
               }
            }, 
            { 
               "id" : "lFoot", 
               "position" : { 
                  "x" : "-0.004174709", 
                  "y" : "-0.472638", 
                  "z" : "0.0005952865"
               }, 
               "rotation" : { 
                  "x" : "11.37427", 
                  "y" : "351.3292", 
                  "z" : "358.2831"
               }
            }, 
            { 
               "id" : "lToe", 
               "position" : { 
                  "x" : "-0.002726519", 
                  "y" : "-0.00646442", 
                  "z" : "0.125921"
               }, 
               "rotation" : { 
                  "x" : "355.4666", 
                  "y" : "359.4682", 
                  "z" : "0.2386294"
               }
            }, 
            { 
               "id" : "lBigToe", 
               "position" : { 
                  "x" : "0.03126174", 
                  "y" : "0.008086237", 
                  "z" : "0.01147882"
               }, 
               "rotation" : { 
                  "x" : "4.62936", 
                  "y" : "355.5412", 
                  "z" : "4.69771"
               }
            }, 
            { 
               "id" : "lSmallToe1", 
               "position" : { 
                  "x" : "0.008659194", 
                  "y" : "0.009396472", 
                  "z" : "0.01628564"
               }, 
               "rotation" : { 
                  "x" : "9.294759", 
                  "y" : "356.6895", 
                  "z" : "4.705157"
               }
            }, 
            { 
               "id" : "lSmallToe2", 
               "position" : { 
                  "x" : "-0.007123746", 
                  "y" : "0.007782519", 
                  "z" : "0.0165536"
               }, 
               "rotation" : { 
                  "x" : "13.96952", 
                  "y" : "358.2888", 
                  "z" : "1.996066"
               }
            }, 
            { 
               "id" : "lSmallToe3", 
               "position" : { 
                  "x" : "-0.01814488", 
                  "y" : "0.00280688", 
                  "z" : "0.01322667"
               }, 
               "rotation" : { 
                  "x" : "15.45807", 
                  "y" : "359.9037", 
                  "z" : "7.3275"
               }
            }, 
            { 
               "id" : "lSmallToe4", 
               "position" : { 
                  "x" : "-0.03400231", 
                  "y" : "-0.002274181", 
                  "z" : "0.009648971"
               }, 
               "rotation" : { 
                  "x" : "18.65026", 
                  "y" : "4.526158", 
                  "z" : "11.87656"
               }
            }, 
            { 
               "id" : "abdomen", 
               "position" : { 
                  "x" : "2.455723E-06", 
                  "y" : "-0.01119356", 
                  "z" : "-0.015187"
               }, 
               "rotation" : { 
                  "x" : "359.99", 
                  "y" : "358.4824", 
                  "z" : "350.0487"
               }
            }, 
            { 
               "id" : "abdomen2", 
               "position" : { 
                  "x" : "4.504621E-05", 
                  "y" : "0.09808062", 
                  "z" : "0.008348306"
               }, 
               "rotation" : { 
                  "x" : "348.1537", 
                  "y" : "358.3172", 
                  "z" : "352.9596"
               }
            }, 
            { 
               "id" : "chest", 
               "position" : { 
                  "x" : "3.760494E-05", 
                  "y" : "0.1310336", 
                  "z" : "0.005795788"
               }, 
               "rotation" : { 
                  "x" : "13.84917", 
                  "y" : "356.6503", 
                  "z" : "0.8689234"
               }
            }, 
            { 
               "id" : "rCollar", 
               "position" : { 
                  "x" : "0.01599506", 
                  "y" : "0.1980567", 
                  "z" : "0.03436312"
               }, 
               "rotation" : { 
                  "x" : "348.4091", 
                  "y" : "5.343095", 
                  "z" : "25.33767"
               }
            }, 
            { 
               "id" : "rShldr", 
               "position" : { 
                  "x" : "0.1289071", 
                  "y" : "-0.03241806", 
                  "z" : "-0.01211328"
               }, 
               "rotation" : { 
                  "x" : "354.4551", 
                  "y" : "315.7033", 
                  "z" : "303.9234"
               }
            }, 
            { 
               "id" : "rForeArm", 
               "position" : { 
                  "x" : "0.2958812", 
                  "y" : "-0.001342773", 
                  "z" : "0.002109662"
               }, 
               "rotation" : { 
                  "x" : "0.3271068", 
                  "y" : "253.3889", 
                  "z" : "356.3942"
               }
            }, 
            { 
               "id" : "rHand", 
               "position" : { 
                  "x" : "0.2321052", 
                  "y" : "-0.0001336541", 
                  "z" : "0.0003476441"
               }, 
               "rotation" : { 
                  "x" : "348.645", 
                  "y" : "345.8976", 
                  "z" : "333.0067"
               }
            }, 
            { 
               "id" : "rCarpal2", 
               "position" : { 
                  "x" : "0.0225851", 
                  "y" : "0.002695912", 
                  "z" : "-0.01120612"
               }, 
               "rotation" : { 
                  "x" : "349.6259", 
                  "y" : "11.16086", 
                  "z" : "354.6041"
               }
            }, 
            { 
               "id" : "rRing1", 
               "position" : { 
                  "x" : "0.05870983", 
                  "y" : "0.003299595", 
                  "z" : "0.01093345"
               }, 
               "rotation" : { 
                  "x" : "5.235782", 
                  "y" : "357.286", 
                  "z" : "347.9199"
               }
            }, 
            { 
               "id" : "rRing2", 
               "position" : { 
                  "x" : "0.03451053", 
                  "y" : "0.001837182", 
                  "z" : "3.542026E-05"
               }, 
               "rotation" : { 
                  "x" : "358.9902", 
                  "y" : "357.6696", 
                  "z" : "342.5966"
               }
            }, 
            { 
               "id" : "rRing3", 
               "position" : { 
                  "x" : "0.02027222", 
                  "y" : "8.947714E-05", 
                  "z" : "-0.0001727968"
               }, 
               "rotation" : { 
                  "x" : "354.5708", 
                  "y" : "358.269", 
                  "z" : "344.6249"
               }
            }, 
            { 
               "id" : "rPinky1", 
               "position" : { 
                  "x" : "0.05418343", 
                  "y" : "-0.002291808", 
                  "z" : "-0.009656469"
               }, 
               "rotation" : { 
                  "x" : "0.9998378", 
                  "y" : "1.017311", 
                  "z" : "351.1898"
               }
            }, 
            { 
               "id" : "rPinky2", 
               "position" : { 
                  "x" : "0.02679664", 
                  "y" : "-4.142506E-05", 
                  "z" : "0.0003908295"
               }, 
               "rotation" : { 
                  "x" : "0.07896086", 
                  "y" : "355.8912", 
                  "z" : "331.4412"
               }
            }, 
            { 
               "id" : "rPinky3", 
               "position" : { 
                  "x" : "0.01605239", 
                  "y" : "0.00157835", 
                  "z" : "-0.0002382629"
               }, 
               "rotation" : { 
                  "x" : "358.834", 
                  "y" : "1.916696", 
                  "z" : "353.5386"
               }
            }, 
            { 
               "id" : "rCarpal1", 
               "position" : { 
                  "x" : "0.02191362", 
                  "y" : "0.004498739", 
                  "z" : "0.01287307"
               }, 
               "rotation" : { 
                  "x" : "0.8840316", 
                  "y" : "354.9304", 
                  "z" : "359.193"
               }
            }, 
            { 
               "id" : "rIndex1", 
               "position" : { 
                  "x" : "0.0613692", 
                  "y" : "0.002429929", 
                  "z" : "0.01024614"
               }, 
               "rotation" : { 
                  "x" : "4.15695", 
                  "y" : "354.9115", 
                  "z" : "346.0465"
               }
            }, 
            { 
               "id" : "rIndex2", 
               "position" : { 
                  "x" : "0.03379187", 
                  "y" : "0.002697191", 
                  "z" : "-0.0003868529"
               }, 
               "rotation" : { 
                  "x" : "359.444", 
                  "y" : "1.695579", 
                  "z" : "342.6294"
               }
            }, 
            { 
               "id" : "rIndex3", 
               "position" : { 
                  "x" : "0.02012768", 
                  "y" : "-0.001718658", 
                  "z" : "-5.991972E-05"
               }, 
               "rotation" : { 
                  "x" : "358.9739", 
                  "y" : "0.560474", 
                  "z" : "345.671"
               }
            }, 
            { 
               "id" : "rMid1", 
               "position" : { 
                  "x" : "0.06279593", 
                  "y" : "0.003451025", 
                  "z" : "-0.01114153"
               }, 
               "rotation" : { 
                  "x" : "359.3375", 
                  "y" : "4.254154", 
                  "z" : "348.3146"
               }
            }, 
            { 
               "id" : "rMid2", 
               "position" : { 
                  "x" : "0.0375092", 
                  "y" : "0.0008557654", 
                  "z" : "0.0002033797"
               }, 
               "rotation" : { 
                  "x" : "357.7361", 
                  "y" : "358.6352", 
                  "z" : "339.253"
               }
            }, 
            { 
               "id" : "rMid3", 
               "position" : { 
                  "x" : "0.02411159", 
                  "y" : "-9.759469E-05", 
                  "z" : "0.0002352464"
               }, 
               "rotation" : { 
                  "x" : "2.100615", 
                  "y" : "2.17646", 
                  "z" : "348.4587"
               }
            }, 
            { 
               "id" : "rThumb1", 
               "position" : { 
                  "x" : "0.0239808", 
                  "y" : "-0.00593296", 
                  "z" : "0.02007288"
               }, 
               "rotation" : { 
                  "x" : "357.7148", 
                  "y" : "304.7365", 
                  "z" : "338.2852"
               }
            }, 
            { 
               "id" : "rThumb2", 
               "position" : { 
                  "x" : "0.04126514", 
                  "y" : "4.502945E-06", 
                  "z" : "-1.117308E-05"
               }, 
               "rotation" : { 
                  "x" : "332.123", 
                  "y" : "28.39506", 
                  "z" : "358.4811"
               }
            }, 
            { 
               "id" : "rThumb3", 
               "position" : { 
                  "x" : "0.02815171", 
                  "y" : "8.627772E-06", 
                  "z" : "-1.513632E-05"
               }, 
               "rotation" : { 
                  "x" : "353.9388", 
                  "y" : "356.8456", 
                  "z" : "1.058164"
               }
            }, 
            { 
               "id" : "lPectoral", 
               "position" : { 
                  "x" : "-0.03002651", 
                  "y" : "0.04602219", 
                  "z" : "-0.04206793"
               }, 
               "rotation" : { 
                  "x" : "348.2751", 
                  "y" : "339.8744", 
                  "z" : "359.9312"
               }
            }, 
            { 
               "id" : "lNipple", 
               "position" : { 
                  "x" : "-0.1949946", 
                  "y" : "0.01042771", 
                  "z" : "0.1335188"
               }, 
               "rotation" : { 
                  "x" : "10.56888", 
                  "y" : "131.8853", 
                  "z" : "354.0328"
               }
            }, 
            { 
               "id" : "lNippleTrigger", 
               "trigger" : { 
                  "displayName" : "lNippleTrigger", 
                  "startActions" : [ 
                  ], 
                  "transitionActions" : [ 
                  ], 
                  "endActions" : [ 
                  ]
               }
            }, 
            { 
               "id" : "rPectoral", 
               "position" : { 
                  "x" : "0.03051426", 
                  "y" : "0.04645656", 
                  "z" : "-0.04005681"
               }, 
               "rotation" : { 
                  "x" : "348.5007", 
                  "y" : "22.13472", 
                  "z" : "0.0285432"
               }
            }, 
            { 
               "id" : "rNipple", 
               "position" : { 
                  "x" : "-0.001108887", 
                  "y" : "0.003031036", 
                  "z" : "0.2059266"
               }, 
               "rotation" : { 
                  "x" : "7.621285", 
                  "y" : "187.2483", 
                  "z" : "11.65142"
               }
            }, 
            { 
               "id" : "rNippleTrigger", 
               "trigger" : { 
                  "displayName" : "rNippleTrigger", 
                  "startActions" : [ 
                  ], 
                  "transitionActions" : [ 
                  ], 
                  "endActions" : [ 
                  ]
               }
            }, 
            { 
               "id" : "neck", 
               "position" : { 
                  "x" : "-0.0001901658", 
                  "y" : "0.2637118", 
                  "z" : "-0.007495776"
               }, 
               "rotation" : { 
                  "x" : "31.3558", 
                  "y" : "3.775791", 
                  "z" : "10.00113"
               }
            }, 
            { 
               "id" : "head", 
               "position" : { 
                  "x" : "0.0004715901", 
                  "y" : "0.08963093", 
                  "z" : "0.0008353442"
               }, 
               "rotation" : { 
                  "x" : "2.676894", 
                  "y" : "358.9305", 
                  "z" : "12.06293"
               }
            }, 
            { 
               "id" : "LipTrigger", 
               "trigger" : { 
                  "displayName" : "LipTrigger", 
                  "startActions" : [ 
                  ], 
                  "transitionActions" : [ 
                  ], 
                  "endActions" : [ 
                  ]
               }
            }, 
            { 
               "id" : "HeadAudioSource", 
               "trigger" : { 
                  "startActions" : [ 
                  ], 
                  "transitionActions" : [ 
                  ], 
                  "endActions" : [ 
                  ]
               }
            }, 
            { 
               "id" : "MouthTrigger", 
               "trigger" : { 
                  "displayName" : "MouthTrigger", 
                  "startActions" : [ 
                  ], 
                  "transitionActions" : [ 
                  ], 
                  "endActions" : [ 
                  ]
               }
            }, 
            { 
               "id" : "ThroatTrigger", 
               "trigger" : { 
                  "displayName" : "ThroatTrigger", 
                  "startActions" : [ 
                  ], 
                  "transitionActions" : [ 
                  ], 
                  "endActions" : [ 
                  ]
               }
            }, 
            { 
               "id" : "rEye", 
               "position" : { 
                  "x" : "0.0313", 
                  "y" : "0.05963699", 
                  "z" : "0.07751656"
               }, 
               "rotation" : { 
                  "x" : "344.0911", 
                  "y" : "24.71462", 
                  "z" : "359.5671"
               }
            }, 
            { 
               "id" : "upperJaw", 
               "position" : { 
                  "x" : "-0.0001", 
                  "y" : "0.0120063", 
                  "z" : "0.02099995"
               }, 
               "rotation" : { 
                  "x" : "0.08960605", 
                  "y" : "359.9898", 
                  "z" : "359.9902"
               }
            }, 
            { 
               "id" : "lEye", 
               "position" : { 
                  "x" : "-0.0313", 
                  "y" : "0.05963699", 
                  "z" : "0.07751656"
               }, 
               "rotation" : { 
                  "x" : "344.0999", 
                  "y" : "25.90228", 
                  "z" : "359.5477"
               }
            }, 
            { 
               "id" : "lowerJaw", 
               "position" : { 
                  "x" : "0.0005828377", 
                  "y" : "0.01188369", 
                  "z" : "0.01834548"
               }, 
               "rotation" : { 
                  "x" : "21.07226", 
                  "y" : "359.946", 
                  "z" : "357.92"
               }
            }, 
            { 
               "id" : "tongueBase", 
               "position" : { 
                  "x" : "0.0005615536", 
                  "y" : "-0.01612615", 
                  "z" : "0.0443517"
               }, 
               "rotation" : { 
                  "x" : "275.0831", 
                  "y" : "179.5287", 
                  "z" : "180.4469"
               }
            }, 
            { 
               "id" : "tongue01", 
               "position" : { 
                  "x" : "0.0004664616", 
                  "y" : "0.00118358", 
                  "z" : "0.00819881"
               }, 
               "rotation" : { 
                  "x" : "45.79617", 
                  "y" : "0.0716731", 
                  "z" : "359.9611"
               }
            }, 
            { 
               "id" : "tongue02", 
               "position" : { 
                  "x" : "0.0001421228", 
                  "y" : "-0.0001775534", 
                  "z" : "0.006548733"
               }, 
               "rotation" : { 
                  "x" : "15.85197", 
                  "y" : "359.9623", 
                  "z" : "-0.001316754"
               }
            }, 
            { 
               "id" : "tongue03", 
               "position" : { 
                  "x" : "0.0001237818", 
                  "y" : "0.0001194129", 
                  "z" : "0.005333858"
               }, 
               "rotation" : { 
                  "x" : "8.201251", 
                  "y" : "-0.004377109", 
                  "z" : "359.9746"
               }
            }, 
            { 
               "id" : "tongue04", 
               "position" : { 
                  "x" : "2.853901E-07", 
                  "y" : "-0.0003121754", 
                  "z" : "0.005026009"
               }, 
               "rotation" : { 
                  "x" : "3.358091", 
                  "y" : "0.0008852516", 
                  "z" : "0.01700445"
               }
            }, 
            { 
               "id" : "tongue05", 
               "position" : { 
                  "x" : "2.624444E-05", 
                  "y" : "-0.0002655294", 
                  "z" : "0.004054139"
               }, 
               "rotation" : { 
                  "x" : "359.3392", 
                  "y" : "-0.005526789", 
                  "z" : "359.9794"
               }
            }, 
            { 
               "id" : "tongueTip", 
               "position" : { 
                  "x" : "-1.062682E-08", 
                  "y" : "-0.0008442507", 
                  "z" : "0.003338329"
               }, 
               "rotation" : { 
                  "x" : "354.2226", 
                  "y" : "0.0005654087", 
                  "z" : "0.003656745"
               }
            }, 
            { 
               "id" : "lCollar", 
               "position" : { 
                  "x" : "-0.01694419", 
                  "y" : "0.1975766", 
                  "z" : "0.03465278"
               }, 
               "rotation" : { 
                  "x" : "347.5372", 
                  "y" : "356.3425", 
                  "z" : "349.202"
               }
            }, 
            { 
               "id" : "lShldr", 
               "position" : { 
                  "x" : "-0.1330355", 
                  "y" : "-0.03768549", 
                  "z" : "-0.01102089"
               }, 
               "rotation" : { 
                  "x" : "7.681971", 
                  "y" : "21.895", 
                  "z" : "52.31675"
               }
            }, 
            { 
               "id" : "lForeArm", 
               "position" : { 
                  "x" : "-0.295777", 
                  "y" : "-0.001393706", 
                  "z" : "0.002157036"
               }, 
               "rotation" : { 
                  "x" : "1.309086", 
                  "y" : "1.852976", 
                  "z" : "355.2077"
               }
            }, 
            { 
               "id" : "lHand", 
               "position" : { 
                  "x" : "-0.2331075", 
                  "y" : "-0.000187719", 
                  "z" : "0.000328351"
               }, 
               "rotation" : { 
                  "x" : "350.6428", 
                  "y" : "334.3102", 
                  "z" : "340.2377"
               }
            }, 
            { 
               "id" : "lCarpal2", 
               "position" : { 
                  "x" : "-0.02340959", 
                  "y" : "0.00226417", 
                  "z" : "-0.01079435"
               }, 
               "rotation" : { 
                  "x" : "349.6175", 
                  "y" : "348.8922", 
                  "z" : "5.432765"
               }
            }, 
            { 
               "id" : "lRing1", 
               "position" : { 
                  "x" : "-0.05947702", 
                  "y" : "0.002855498", 
                  "z" : "0.01139637"
               }, 
               "rotation" : { 
                  "x" : "5.223332", 
                  "y" : "2.72269", 
                  "z" : "12.05316"
               }
            }, 
            { 
               "id" : "lRing2", 
               "position" : { 
                  "x" : "-0.03538159", 
                  "y" : "0.001604055", 
                  "z" : "0.0004979673"
               }, 
               "rotation" : { 
                  "x" : "359.2036", 
                  "y" : "2.98137", 
                  "z" : "16.8175"
               }
            }, 
            { 
               "id" : "lRing3", 
               "position" : { 
                  "x" : "-0.02119393", 
                  "y" : "0.0001134647", 
                  "z" : "0.0002447312"
               }, 
               "rotation" : { 
                  "x" : "353.2908", 
                  "y" : "1.391589", 
                  "z" : "15.30812"
               }
            }, 
            { 
               "id" : "lPinky1", 
               "position" : { 
                  "x" : "-0.05495935", 
                  "y" : "-0.002750787", 
                  "z" : "-0.009178715"
               }, 
               "rotation" : { 
                  "x" : "0.9741192", 
                  "y" : "359.041", 
                  "z" : "8.833233"
               }
            }, 
            { 
               "id" : "lPinky2", 
               "position" : { 
                  "x" : "-0.02761647", 
                  "y" : "-0.0003523016", 
                  "z" : "0.0008713092"
               }, 
               "rotation" : { 
                  "x" : "359.8228", 
                  "y" : "3.970248", 
                  "z" : "28.40029"
               }
            }, 
            { 
               "id" : "lPinky3", 
               "position" : { 
                  "x" : "-0.01694021", 
                  "y" : "0.001712237", 
                  "z" : "0.0002325682"
               }, 
               "rotation" : { 
                  "x" : "358.8477", 
                  "y" : "358.4126", 
                  "z" : "6.303819"
               }
            }, 
            { 
               "id" : "lCarpal1", 
               "position" : { 
                  "x" : "-0.02274309", 
                  "y" : "0.004071136", 
                  "z" : "0.01327903"
               }, 
               "rotation" : { 
                  "x" : "0.8801162", 
                  "y" : "5.103594", 
                  "z" : "0.8279455"
               }
            }, 
            { 
               "id" : "lIndex1", 
               "position" : { 
                  "x" : "-0.06222389", 
                  "y" : "0.00202795", 
                  "z" : "0.01057488"
               }, 
               "rotation" : { 
                  "x" : "3.293616", 
                  "y" : "5.026543", 
                  "z" : "13.92575"
               }
            }, 
            { 
               "id" : "lIndex2", 
               "position" : { 
                  "x" : "-0.03475981", 
                  "y" : "0.002534393", 
                  "z" : "-0.0001072361"
               }, 
               "rotation" : { 
                  "x" : "358.6494", 
                  "y" : "358.0919", 
                  "z" : "17.3551"
               }
            }, 
            { 
               "id" : "lIndex3", 
               "position" : { 
                  "x" : "-0.02105171", 
                  "y" : "-0.001527758", 
                  "z" : "0.0002715237"
               }, 
               "rotation" : { 
                  "x" : "358.8864", 
                  "y" : "359.7417", 
                  "z" : "14.20438"
               }
            }, 
            { 
               "id" : "lMid1", 
               "position" : { 
                  "x" : "-0.06365389", 
                  "y" : "0.003060172", 
                  "z" : "-0.01082396"
               }, 
               "rotation" : { 
                  "x" : "359.3148", 
                  "y" : "355.8006", 
                  "z" : "11.68692"
               }
            }, 
            { 
               "id" : "lMid2", 
               "position" : { 
                  "x" : "-0.03841934", 
                  "y" : "0.0006209473", 
                  "z" : "0.0005924267"
               }, 
               "rotation" : { 
                  "x" : "357.3475", 
                  "y" : "1.235689", 
                  "z" : "20.65451"
               }
            }, 
            { 
               "id" : "lMid3", 
               "position" : { 
                  "x" : "-0.02502015", 
                  "y" : "4.054111E-05", 
                  "z" : "0.0006296381"
               }, 
               "rotation" : { 
                  "x" : "1.997207", 
                  "y" : "358.172", 
                  "z" : "11.35222"
               }
            }, 
            { 
               "id" : "lThumb1", 
               "position" : { 
                  "x" : "-0.0248026", 
                  "y" : "-0.006364549", 
                  "z" : "0.02048629"
               }, 
               "rotation" : { 
                  "x" : "357.607", 
                  "y" : "55.44327", 
                  "z" : "21.75061"
               }
            }, 
            { 
               "id" : "lThumb2", 
               "position" : { 
                  "x" : "-0.04216537", 
                  "y" : "-7.771887E-05", 
                  "z" : "-0.00046374"
               }, 
               "rotation" : { 
                  "x" : "332.1212", 
                  "y" : "331.7109", 
                  "z" : "1.61386"
               }
            }, 
            { 
               "id" : "lThumb3", 
               "position" : { 
                  "x" : "-0.02916211", 
                  "y" : "-6.168615E-05", 
                  "z" : "-1.829513E-05"
               }, 
               "rotation" : { 
                  "x" : "353.9828", 
                  "y" : "3.138757", 
                  "z" : "358.9658"
               }
            }
         ]
      }, 
      { 
         "id" : "AnimationPatternStep1", 
         "on" : "true", 
         "type" : "AnimationStep", 
         "parentAtom" : "AnimationPattern", 
         "position" : { 
            "x" : "1.8", 
            "y" : "2.8", 
            "z" : "0"
         }, 
         "rotation" : { 
            "x" : "0", 
            "y" : "0", 
            "z" : "0"
         }, 
         "containerPosition" : { 
            "x" : "1", 
            "y" : "1.735246", 
            "z" : "0.4"
         }, 
         "containerRotation" : { 
            "x" : "0", 
            "y" : "230", 
            "z" : "-2.142587E-07"
         }, 
         "storables" : [ 
            { 
               "id" : "CollisionTrigger", 
               "trigger" : { 
                  "startActions" : [ 
                  ], 
                  "transitionActions" : [ 
                  ], 
                  "endActions" : [ 
                  ]
               }
            }, 
            { 
               "id" : "Step", 
               "trigger" : { 
                  "startActions" : [ 
                  ], 
                  "transitionActions" : [ 
                  ], 
                  "endActions" : [ 
                  ]
               }
            }, 
            { 
               "id" : "controlPointIn", 
               "position" : { 
                  "x" : "1.242438", 
                  "y" : "1.755044", 
                  "z" : "0.4444444"
               }, 
               "rotation" : { 
                  "x" : "0", 
                  "y" : "230", 
                  "z" : "-2.142587E-07"
               }
            }, 
            { 
               "id" : "controlPointOut", 
               "position" : { 
                  "x" : "0.7575617", 
                  "y" : "1.715448", 
                  "z" : "0.3555556"
               }, 
               "rotation" : { 
                  "x" : "0", 
                  "y" : "230", 
                  "z" : "-2.142587E-07"
               }
            }, 
            { 
               "id" : "PluginManager", 
               "plugins" : { 
               }
            }, 
            { 
               "id" : "control", 
               "position" : { 
                  "x" : "1", 
                  "y" : "1.735246", 
                  "z" : "0.4"
               }, 
               "rotation" : { 
                  "x" : "0", 
                  "y" : "230", 
                  "z" : "-2.142587E-07"
               }
            }
         ]
      }, 
      { 
         "id" : "InvisibleLight#Fill", 
         "on" : "true", 
         "type" : "InvisibleLight", 
         "position" : { 
            "x" : "0.29", 
            "y" : "1.833", 
            "z" : "0.238"
         }, 
         "rotation" : { 
            "x" : "0", 
            "y" : "0", 
            "z" : "0"
         }, 
         "containerPosition" : { 
            "x" : "-0.8631204", 
            "y" : "1.313873", 
            "z" : "1.31393"
         }, 
         "containerRotation" : { 
            "x" : "313.485", 
            "y" : "117.63", 
            "z" : "332.0023"
         }, 
         "storables" : [ 
            { 
               "id" : "CollisionTrigger", 
               "trigger" : { 
                  "startActions" : [ 
                  ], 
                  "transitionActions" : [ 
                  ], 
                  "endActions" : [ 
                  ]
               }
            }, 
            { 
               "id" : "Light", 
               "shadowsOn" : "false", 
               "intensity" : "2.141953", 
               "range" : "8.845633", 
               "renderType" : "ForceVertex"
            }, 
            { 
               "id" : "PluginManager", 
               "plugins" : { 
               }
            }, 
            { 
               "id" : "control", 
               "position" : { 
                  "x" : "-0.8631204", 
                  "y" : "1.313873", 
                  "z" : "1.31393"
               }, 
               "rotation" : { 
                  "x" : "313.485", 
                  "y" : "117.63", 
                  "z" : "332.0023"
               }
            }
         ]
      }, 
      { 
         "id" : "ReflectiveWoodPanel", 
         "on" : "true", 
         "type" : "ReflectiveWoodPanel", 
         "position" : { 
            "x" : "-0.6", 
            "y" : "0", 
            "z" : "0"
         }, 
         "rotation" : { 
            "x" : "0", 
            "y" : "0", 
            "z" : "0"
         }, 
         "containerPosition" : { 
            "x" : "-0.6", 
            "y" : "0", 
            "z" : "0"
         }, 
         "containerRotation" : { 
            "x" : "0", 
            "y" : "0", 
            "z" : "0"
         }, 
         "storables" : [ 
            { 
               "id" : "CollisionTrigger", 
               "trigger" : { 
                  "startActions" : [ 
                  ], 
                  "transitionActions" : [ 
                  ], 
                  "endActions" : [ 
                  ]
               }
            }, 
            { 
               "id" : "MirrorRender", 
               "reflectionOpacity" : "0.5492792", 
               "specularIntensity" : "0.3378106", 
               "reflectionColor" : { 
                  "h" : "0", 
                  "s" : "0", 
                  "v" : "1"
               }
            }, 
            { 
               "id" : "PluginManager", 
               "plugins" : { 
               }
            }, 
            { 
               "id" : "control", 
               "position" : { 
                  "x" : "-0.6", 
                  "y" : "0", 
                  "z" : "0"
               }, 
               "rotation" : { 
                  "x" : "0", 
                  "y" : "0", 
                  "z" : "0"
               }
            }
         ]
      }, 
      { 
         "id" : "AnimationPattern", 
         "on" : "true", 
         "type" : "AnimationPattern", 
         "position" : { 
            "x" : "1.1", 
            "y" : "2.8", 
            "z" : "0"
         }, 
         "rotation" : { 
            "x" : "0", 
            "y" : "0", 
            "z" : "0"
         }, 
         "containerPosition" : { 
            "x" : "1.1", 
            "y" : "0.7885008", 
            "z" : "0"
         }, 
         "containerRotation" : { 
            "x" : "0", 
            "y" : "0", 
            "z" : "0"
         }, 
         "storables" : [ 
            { 
               "id" : "CollisionTrigger", 
               "trigger" : { 
                  "startActions" : [ 
                  ], 
                  "transitionActions" : [ 
                  ], 
                  "endActions" : [ 
                  ]
               }
            }, 
            { 
               "id" : "AnimationPattern", 
               "currentTime" : "0.7788086", 
               "steps" : [ 
                  "AnimationPatternStep1", 
                  "AnimationPatternStep2"
               ], 
               "triggers" : [ 
                  { 
                     "startActions" : [ 
                     ], 
                     "transitionActions" : [ 
                     ], 
                     "endActions" : [ 
                        { 
                           "receiverAtom" : "AnimationPattern", 
                           "receiverTargetName" : "Active", 
                           "boolValue" : "false"
                        }
                     ], 
                     "startTime" : "0", 
                     "endTime" : "2"
                  }
               ]
            }, 
            { 
               "id" : "PluginManager", 
               "plugins" : { 
                  "plugin#0" : "Saves/Scripts/AcidBubbles/Director/src/Director.cs"
               }
            }, 
            { 
               "id" : "control", 
               "position" : { 
                  "x" : "1.1", 
                  "y" : "0.7885008", 
                  "z" : "0"
               }, 
               "rotation" : { 
                  "x" : "0", 
                  "y" : "0", 
                  "z" : "0"
               }
            }
         ]
      }, 
      { 
         "id" : "InvisibleLight#Main", 
         "on" : "true", 
         "type" : "InvisibleLight", 
         "position" : { 
            "x" : "0.29", 
            "y" : "1.833", 
            "z" : "0.238"
         }, 
         "rotation" : { 
            "x" : "0", 
            "y" : "0", 
            "z" : "0"
         }, 
         "containerPosition" : { 
            "x" : "0.4270489", 
            "y" : "1.823992", 
            "z" : "1.98007"
         }, 
         "containerRotation" : { 
            "x" : "21.25465", 
            "y" : "189.0726", 
            "z" : "244.9871"
         }, 
         "storables" : [ 
            { 
               "id" : "CollisionTrigger", 
               "trigger" : { 
                  "startActions" : [ 
                  ], 
                  "transitionActions" : [ 
                  ], 
                  "endActions" : [ 
                  ]
               }
            }, 
            { 
               "id" : "Light", 
               "intensity" : "4.366878", 
               "range" : "9.256413", 
               "spotAngle" : "65.03468", 
               "shadowStrength" : "0.1736278", 
               "type" : "Spot", 
               "renderType" : "ForcePixel", 
               "shadowResolution" : "High", 
               "color" : { 
                  "h" : "0.1147204", 
                  "s" : "0.128829", 
                  "v" : "0.971307"
               }
            }, 
            { 
               "id" : "PluginManager", 
               "plugins" : { 
               }
            }, 
            { 
               "id" : "control", 
               "position" : { 
                  "x" : "0.4270489", 
                  "y" : "1.823992", 
                  "z" : "1.98007"
               }, 
               "rotation" : { 
                  "x" : "21.25465", 
                  "y" : "189.0726", 
                  "z" : "244.9871"
               }
            }
         ]
      }, 
      { 
         "id" : "InvisibleLight#Back", 
         "on" : "true", 
         "type" : "InvisibleLight", 
         "position" : { 
            "x" : "0.29", 
            "y" : "1.833", 
            "z" : "0.238"
         }, 
         "rotation" : { 
            "x" : "0", 
            "y" : "0", 
            "z" : "0"
         }, 
         "containerPosition" : { 
            "x" : "-0.911206", 
            "y" : "1.723626", 
            "z" : "-0.546046"
         }, 
         "containerRotation" : { 
            "x" : "17.64422", 
            "y" : "43.70493", 
            "z" : "27.05936"
         }, 
         "storables" : [ 
            { 
               "id" : "CollisionTrigger", 
               "trigger" : { 
                  "startActions" : [ 
                  ], 
                  "transitionActions" : [ 
                  ], 
                  "endActions" : [ 
                  ]
               }
            }, 
            { 
               "id" : "Light", 
               "shadowsOn" : "false", 
               "intensity" : "4.9252", 
               "range" : "5.913548", 
               "spotAngle" : "36.96177", 
               "type" : "Spot", 
               "renderType" : "ForceVertex", 
               "color" : { 
                  "h" : "0.9554788", 
                  "s" : "0.05496208", 
                  "v" : "1"
               }
            }, 
            { 
               "id" : "PluginManager", 
               "plugins" : { 
               }
            }, 
            { 
               "id" : "control", 
               "position" : { 
                  "x" : "-0.911206", 
                  "y" : "1.723626", 
                  "z" : "-0.546046"
               }, 
               "rotation" : { 
                  "x" : "17.64422", 
                  "y" : "43.70493", 
                  "z" : "27.05936"
               }
            }
         ]
      }, 
      { 
         "id" : "AnimationPatternStep2", 
         "on" : "true", 
         "type" : "AnimationStep", 
         "parentAtom" : "AnimationPattern", 
         "position" : { 
            "x" : "1.8", 
            "y" : "2.8", 
            "z" : "0"
         }, 
         "rotation" : { 
            "x" : "0", 
            "y" : "0", 
            "z" : "0"
         }, 
         "containerPosition" : { 
            "x" : "-1.181945", 
            "y" : "1.557063", 
            "z" : "0"
         }, 
         "containerRotation" : { 
            "x" : "0", 
            "y" : "90", 
            "z" : "0"
         }, 
         "storables" : [ 
            { 
               "id" : "CollisionTrigger", 
               "trigger" : { 
                  "startActions" : [ 
                  ], 
                  "transitionActions" : [ 
                  ], 
                  "endActions" : [ 
                  ]
               }
            }, 
            { 
               "id" : "Step", 
               "trigger" : { 
                  "startActions" : [ 
                  ], 
                  "transitionActions" : [ 
                  ], 
                  "endActions" : [ 
                  ]
               }
            }, 
            { 
               "id" : "controlPointIn", 
               "position" : { 
                  "x" : "-0.9395069", 
                  "y" : "1.576861", 
                  "z" : "0.04444446"
               }, 
               "rotation" : { 
                  "x" : "0", 
                  "y" : "90", 
                  "z" : "0"
               }
            }, 
            { 
               "id" : "controlPointOut", 
               "position" : { 
                  "x" : "-1.424384", 
                  "y" : "1.537265", 
                  "z" : "-0.04444446"
               }, 
               "rotation" : { 
                  "x" : "0", 
                  "y" : "90", 
                  "z" : "0"
               }
            }, 
            { 
               "id" : "PluginManager", 
               "plugins" : { 
               }
            }, 
            { 
               "id" : "control", 
               "position" : { 
                  "x" : "-1.181945", 
                  "y" : "1.557063", 
                  "z" : "0"
               }, 
               "rotation" : { 
                  "x" : "0", 
                  "y" : "90", 
                  "z" : "0"
               }
            }
         ]
      }, 
      { 
         "id" : "UIButton", 
         "on" : "true", 
         "type" : "UIButton", 
         "position" : { 
            "x" : "1.4", 
            "y" : "1", 
            "z" : "0"
         }, 
         "rotation" : { 
            "x" : "0", 
            "y" : "0", 
            "z" : "0"
         }, 
         "containerPosition" : { 
            "x" : "-0.5362484", 
            "y" : "1", 
            "z" : "0"
         }, 
         "containerRotation" : { 
            "x" : "0", 
            "y" : "45.57125", 
            "z" : "0"
         }, 
         "storables" : [ 
            { 
               "id" : "CollisionTrigger", 
               "trigger" : { 
                  "startActions" : [ 
                  ], 
                  "transitionActions" : [ 
                  ], 
                  "endActions" : [ 
                  ]
               }
            }, 
            { 
               "id" : "Trigger", 
               "trigger" : { 
                  "startActions" : [ 
                     { 
                        "receiverAtom" : "AnimationPattern", 
                        "receiverTargetName" : "Active", 
                        "boolValue" : "true"
                     }, 
                     { 
                        "receiverAtom" : "AnimationPattern", 
                        "receiver" : "AnimationPattern", 
                        "receiverTargetName" : "ResetAndPlay"
                     }
                  ], 
                  "transitionActions" : [ 
                  ], 
                  "endActions" : [ 
                  ]
               }
            }, 
            { 
               "id" : "PluginManager", 
               "plugins" : { 
               }
            }, 
            { 
               "id" : "control", 
               "position" : { 
                  "x" : "-0.5362484", 
                  "y" : "1", 
                  "z" : "0"
               }, 
               "rotation" : { 
                  "x" : "0", 
                  "y" : "45.57125", 
                  "z" : "0"
               }
            }
         ]
      }
   ]
}